sunkit_magex/__init__.py
sunkit_magex/_version.py
sunkit_magex/version.py
sunkit_magex/pfss/__init__.py
sunkit_magex/pfss/analytic.py
sunkit_magex/pfss/coords.py
sunkit_magex/pfss/fieldline.py
sunkit_magex/pfss/grid.py
sunkit_magex/pfss/input.py
sunkit_magex/pfss/interpolator.py
sunkit_magex/pfss/output.py
sunkit_magex/pfss/pfss.py
sunkit_magex/pfss/sample_data.py
sunkit_magex/pfss/tracing.py
sunkit_magex/pfss/utils.py
sunkit_magex/pfss/tests/__init__.py
sunkit_magex/pfss/tests/conftest.py
sunkit_magex/pfss/tests/test_analytic.py
sunkit_magex/pfss/tests/test_coords.py
sunkit_magex/pfss/tests/test_fieldline.py
sunkit_magex/pfss/tests/test_pfss.py
sunkit_magex/pfss/tests/test_tracers.py
sunkit_magex/pfss/tests/test_utils.py
sunkit_magex/pfss/tests/arraydiff_reference/test_pfss.txt
sunkit_magex/pfss/tests/data/adapt_header.header
sunkit_magex/pfss/tests/data/br_in.txt
sunkit_magex/pfss/tests/data/gong_header.header
sunkit_magex/tests/__init__.py
sunkit_magex/tests/helpers.py
sunkit_magex-1.1.0.dist-info/METADATA
sunkit_magex-1.1.0.dist-info/WHEEL
sunkit_magex-1.1.0.dist-info/top_level.txt
sunkit_magex-1.1.0.dist-info/RECORD
