Metadata-Version: 2.4
Name: sunkit_magex
Version: 1.1.0
Summary: Solar Magnetic field Extrapolation
Author: David Stansby
Author-email: The SunPy Community <sunpy@googlegroups.com>
License: Copyright (C) 2024, The SunPy Community
Project-URL: Homepage, https://sunpy.org
Project-URL: Download, https://pypi.org/project/sunkit-magex/
Project-URL: Source Code, https://github.com/sunpy/sunkit-magex/
Project-URL: Documentation, https://docs.sunpy.org/projects/sunkit-magex/en/stable/
Project-URL: Changelog, https://docs.sunpy.org/en/stable/whatsnew/changelog.html
Project-URL: Issue Tracker, https://github.com/sunpy/sunkit-magex/issues
Requires-Python: >=3.10
Requires-Dist: astropy>=5.3.0
Requires-Dist: numpy>=1.23.5
Requires-Dist: scikit-image>=0.19.0
Requires-Dist: scipy>=1.10.1
Requires-Dist: streamtracer>=2.2.0
Requires-Dist: sunpy[map]!=6.0.0,>=6.0.1
Requires-Dist: matplotlib>=3.6.0
Provides-Extra: tests
Requires-Dist: pytest; extra == "tests"
Requires-Dist: pytest-doctestplus; extra == "tests"
Requires-Dist: pytest-cov; extra == "tests"
Requires-Dist: pytest-xdist; extra == "tests"
Requires-Dist: pytest-arraydiff; extra == "tests"
Requires-Dist: parfive; extra == "tests"
Requires-Dist: reproject; extra == "tests"
Requires-Dist: sunkit-magex[all]; extra == "tests"
Provides-Extra: docs
Requires-Dist: sphinx; extra == "docs"
Requires-Dist: sphinx-automodapi; extra == "docs"
Requires-Dist: sphinx-changelog; extra == "docs"
Requires-Dist: sunpy-sphinx-theme; extra == "docs"
Requires-Dist: packaging; extra == "docs"
Requires-Dist: reproject; extra == "docs"
Requires-Dist: sphinx-gallery; extra == "docs"
Requires-Dist: sunpy[map,net]!=6.0.0,>=6.0.1; extra == "docs"
Requires-Dist: sunkit-magex[all]; extra == "docs"
Provides-Extra: performance
Requires-Dist: numba; extra == "performance"
Provides-Extra: analytic
Requires-Dist: sympy; extra == "analytic"
Provides-Extra: all
Requires-Dist: sunkit-magex[analytic,performance]; extra == "all"
Provides-Extra: dev
Requires-Dist: sunkit-magex[all,docs,tests]; extra == "dev"
